jupyterlab_darkside_theme/__init__.py
jupyterlab_darkside_theme/_version.py
jupyterlab_darkside_theme-0.1.2.data/data/share/jupyter/labextensions/jupyterlab_darkside_theme/package.json
jupyterlab_darkside_theme-0.1.2.data/data/share/jupyter/labextensions/jupyterlab_darkside_theme/static/568.cfcc7854f14580e5bd88.js
jupyterlab_darkside_theme-0.1.2.data/data/share/jupyter/labextensions/jupyterlab_darkside_theme/static/remoteEntry.e86ff50f95440e8c1172.js
jupyterlab_darkside_theme-0.1.2.data/data/share/jupyter/labextensions/jupyterlab_darkside_theme/static/style.js
jupyterlab_darkside_theme-0.1.2.data/data/share/jupyter/labextensions/jupyterlab_darkside_theme/static/third-party-licenses.json
jupyterlab_darkside_theme-0.1.2.data/data/share/jupyter/labextensions/jupyterlab_darkside_theme/themes/jupyterlab_darkside_theme/index.css
jupyterlab_darkside_theme-0.1.2.data/data/share/jupyter/labextensions/jupyterlab_darkside_theme/themes/jupyterlab_darkside_theme/index.js
jupyterlab_darkside_theme-0.1.2.data/data/share/jupyter/labextensions/jupyterlab_darkside_theme/install.json
jupyterlab_darkside_theme-0.1.2.dist-info/METADATA
jupyterlab_darkside_theme-0.1.2.dist-info/WHEEL
jupyterlab_darkside_theme-0.1.2.dist-info/licenses/LICENSE
jupyterlab_darkside_theme-0.1.2.dist-info/RECORD
